psdl/__init__.py
psdl/cli.py
psdl/expression_parser.py
psdl/mapping.py
psdl/operators.py
psdl/py.typed
psdl/_generated/__init__.py
psdl/_generated/ast_types.py
psdl/_generated/conformance_tests.py
psdl/_generated/operators_meta.py
psdl/_generated/schema_types.py
psdl/_generated/sql_templates.py
psdl/_generated/transformer.py
psdl/_generated/validate.py
psdl/adapters/__init__.py
psdl/adapters/fhir.py
psdl/adapters/omop.py
psdl/adapters/physionet.py
psdl/benchmarks/__init__.py
psdl/benchmarks/data_generator.py
psdl/benchmarks/runner.py
psdl/benchmarks/scenarios.py
psdl/core/__init__.py
psdl/core/compile.py
psdl/core/dataset.py
psdl/core/ir.py
psdl/core/loader.py
psdl/core/normalize.py
psdl/core/parser.py
psdl/examples/__init__.py
psdl/examples/aki_detection.yaml
psdl/examples/hemorrhage_detection.yaml
psdl/examples/hyperkalemia_detection.yaml
psdl/examples/icu_deterioration.yaml
psdl/examples/lactic_acidosis.yaml
psdl/examples/physionet_sepsis.yaml
psdl/examples/sepsis_screening.yaml
psdl/execution/__init__.py
psdl/execution/batch.py
psdl/execution/sql_compiler.py
psdl/execution/streaming/__init__.py
psdl/execution/streaming/compiler.py
psdl/execution/streaming/config.py
psdl/execution/streaming/flink_runtime.py
psdl/execution/streaming/models.py
psdl/execution/streaming/operators.py
psdl/runtimes/__init__.py
psdl/runtimes/cohort/__init__.py
psdl/runtimes/cohort/compiler.py
psdl/runtimes/single/__init__.py
psdl/runtimes/single/evaluator.py
psdl_lang-0.3.2.dist-info/licenses/LICENSE
psdl_lang-0.3.2.dist-info/METADATA
psdl_lang-0.3.2.dist-info/WHEEL
psdl_lang-0.3.2.dist-info/entry_points.txt
psdl_lang-0.3.2.dist-info/top_level.txt
psdl_lang-0.3.2.dist-info/RECORD
