Metadata-Version: 2.4
Name: psdl-lang
Version: 0.3.2
Summary: Patient Scenario Definition Language - Reference Implementation
Author-email: Ziyuan Guan <ziyuan.guan@ufl.edu>
Maintainer-email: Ziyuan Guan <ziyuan.guan@ufl.edu>
License: Apache-2.0
Project-URL: Homepage, https://github.com/Chesterguan/PSDL
Project-URL: Documentation, https://github.com/Chesterguan/PSDL#readme
Project-URL: Repository, https://github.com/Chesterguan/PSDL
Project-URL: Issues, https://github.com/Chesterguan/PSDL/issues
Project-URL: Changelog, https://github.com/Chesterguan/PSDL/blob/main/CHANGELOG.md
Keywords: healthcare,clinical,patient,scenario,DSL,OMOP,FHIR,EHR,temporal,medical
Classifier: Development Status :: 4 - Beta
Classifier: Intended Audience :: Healthcare Industry
Classifier: Intended Audience :: Science/Research
Classifier: Intended Audience :: Developers
Classifier: Operating System :: OS Independent
Classifier: Programming Language :: Python :: 3
Classifier: Programming Language :: Python :: 3.8
Classifier: Programming Language :: Python :: 3.9
Classifier: Programming Language :: Python :: 3.10
Classifier: Programming Language :: Python :: 3.11
Classifier: Programming Language :: Python :: 3.12
Classifier: Topic :: Scientific/Engineering :: Medical Science Apps.
Classifier: Topic :: Software Development :: Libraries :: Python Modules
Classifier: Typing :: Typed
Requires-Python: >=3.8
License-File: LICENSE
Requires-Dist: pyyaml>=6.0
Provides-Extra: full
Requires-Dist: requests>=2.28; extra == "full"
Requires-Dist: sqlalchemy>=2.0; extra == "full"
Provides-Extra: omop
Requires-Dist: sqlalchemy>=2.0; extra == "omop"
Provides-Extra: fhir
Requires-Dist: requests>=2.28; extra == "fhir"
Provides-Extra: streaming
Requires-Dist: apache-flink>=1.17; extra == "streaming"
Provides-Extra: dev
Requires-Dist: pytest>=7.0; extra == "dev"
Requires-Dist: pytest-cov>=4.0; extra == "dev"
Requires-Dist: jsonschema>=4.0; extra == "dev"
Requires-Dist: lark>=1.1; extra == "dev"
Requires-Dist: black>=23.0; extra == "dev"
Requires-Dist: isort>=5.12; extra == "dev"
Requires-Dist: mypy>=1.0; extra == "dev"
Requires-Dist: requests>=2.28; extra == "dev"
Provides-Extra: docs
Requires-Dist: sphinx>=6.0; extra == "docs"
Requires-Dist: sphinx-rtd-theme>=1.3; extra == "docs"
Requires-Dist: myst-parser>=2.0; extra == "docs"
Provides-Extra: notebook
Requires-Dist: jupyter>=1.0; extra == "notebook"
Requires-Dist: ipywidgets>=8.0; extra == "notebook"
Requires-Dist: pandas>=2.0; extra == "notebook"
Requires-Dist: matplotlib>=3.7; extra == "notebook"
Provides-Extra: all
Requires-Dist: psdl-lang[dev,docs,full,notebook,streaming]; extra == "all"
Dynamic: license-file
